wechat_push/__init__.py
wechat_push-1.0.1.dist-info/LICENSE
wechat_push-1.0.1.dist-info/METADATA
wechat_push-1.0.1.dist-info/WHEEL
wechat_push-1.0.1.dist-info/top_level.txt
wechat_push-1.0.1.dist-info/RECORD
