Metadata-Version: 2.1
Name: wechat-push
Version: 1.0.1
Summary: Push your messages to wechat easily.
Home-page: https://github.com/lyc8503/WechatPush
Author: lyc8503
Author-email: lyc8503@foxmail.com
License: UNKNOWN
Platform: UNKNOWN
Classifier: Programming Language :: Python :: 3
Classifier: License :: OSI Approved :: GNU General Public License v3 (GPLv3)
Classifier: Operating System :: OS Independent
Requires-Python: >=3.5
License-File: LICENSE
Requires-Dist: requests (>=2.27.1)
